{"version":"3","listProblem":[{
  "tool": "Code Inspection",
  "category": "Redundant constructs",
  "type": "Unused symbol",
  "tags": [
    "kotlin"
  ],
  "severity": "High",
  "comment": "Function \"ansiColor\" is never used",
  "detailsInfo": "Reports symbols that are not used or not reachable from entry points.",
  "sources": [
    {
      "type": "file",
      "path": "kotlin-stdlib/commonMain/kotlin/com/javiersc/kotlin/stdlib/AnsiColors.kt",
      "language": "kotlin",
      "line": 3,
      "offset": 25,
      "length": 9,
      "code": {
        "startLine": 1,
        "length": 9,
        "offset": 61,
        "surroundingCode": "package com.javiersc.kotlin.stdlib\n\npublic inline fun String.ansiColor(color: AnsiColor): String = \"${color}$this${AnsiColor.Reset}\"\n\npublic abstract class AnsiColor {"
      }
    }
  ],
  "attributes": {
    "module": "kotlin-stdlib-javiersc.kotlin-stdlib.commonMain",
    "inspectionName": "UnusedSymbol"
  },
  "hash": "5048059621509776234"
},{
  "tool": "Code Inspection",
  "category": "Redundant constructs",
  "type": "Unused symbol",
  "tags": [
    "kotlin"
  ],
  "severity": "High",
  "comment": "Object \"Foreground\" is never used",
  "detailsInfo": "Reports symbols that are not used or not reachable from entry points.",
  "sources": [
    {
      "type": "file",
      "path": "kotlin-stdlib/commonMain/kotlin/com/javiersc/kotlin/stdlib/AnsiColors.kt",
      "language": "kotlin",
      "line": 15,
      "offset": 18,
      "length": 10,
      "code": {
        "startLine": 13,
        "length": 10,
        "offset": 25,
        "surroundingCode": "    }\n\n    public object Foreground {\n        public object Black : AnsiColor() {\n            override val value: String = \"\\u001B[30m\""
      }
    }
  ],
  "attributes": {
    "module": "kotlin-stdlib-javiersc.kotlin-stdlib.commonMain",
    "inspectionName": "UnusedSymbol"
  },
  "hash": "8116375750341824956"
},{
  "tool": "Code Inspection",
  "category": "Redundant constructs",
  "type": "Unused symbol",
  "tags": [
    "kotlin"
  ],
  "severity": "High",
  "comment": "Object \"Black\" is never used",
  "detailsInfo": "Reports symbols that are not used or not reachable from entry points.",
  "sources": [
    {
      "type": "file",
      "path": "kotlin-stdlib/commonMain/kotlin/com/javiersc/kotlin/stdlib/AnsiColors.kt",
      "language": "kotlin",
      "line": 16,
      "offset": 22,
      "length": 5,
      "code": {
        "startLine": 14,
        "length": 5,
        "offset": 54,
        "surroundingCode": "\n    public object Foreground {\n        public object Black : AnsiColor() {\n            override val value: String = \"\\u001B[30m\"\n        }"
      }
    }
  ],
  "attributes": {
    "module": "kotlin-stdlib-javiersc.kotlin-stdlib.commonMain",
    "inspectionName": "UnusedSymbol"
  },
  "hash": "6710597369734303259"
},{
  "tool": "Code Inspection",
  "category": "Redundant constructs",
  "type": "Unused symbol",
  "tags": [
    "kotlin"
  ],
  "severity": "High",
  "comment": "Object \"Red\" is never used",
  "detailsInfo": "Reports symbols that are not used or not reachable from entry points.",
  "sources": [
    {
      "type": "file",
      "path": "kotlin-stdlib/commonMain/kotlin/com/javiersc/kotlin/stdlib/AnsiColors.kt",
      "language": "kotlin",
      "line": 19,
      "offset": 22,
      "length": 3,
      "code": {
        "startLine": 17,
        "length": 3,
        "offset": 86,
        "surroundingCode": "            override val value: String = \"\\u001B[30m\"\n        }\n        public object Red : AnsiColor() {\n            override val value: String = \"\\u001B[31m\"\n        }"
      }
    }
  ],
  "attributes": {
    "module": "kotlin-stdlib-javiersc.kotlin-stdlib.commonMain",
    "inspectionName": "UnusedSymbol"
  },
  "hash": "7873034914762994074"
},{
  "tool": "Code Inspection",
  "category": "Redundant constructs",
  "type": "Unused symbol",
  "tags": [
    "kotlin"
  ],
  "severity": "High",
  "comment": "Object \"Green\" is never used",
  "detailsInfo": "Reports symbols that are not used or not reachable from entry points.",
  "sources": [
    {
      "type": "file",
      "path": "kotlin-stdlib/commonMain/kotlin/com/javiersc/kotlin/stdlib/AnsiColors.kt",
      "language": "kotlin",
      "line": 22,
      "offset": 22,
      "length": 5,
      "code": {
        "startLine": 20,
        "length": 5,
        "offset": 86,
        "surroundingCode": "            override val value: String = \"\\u001B[31m\"\n        }\n        public object Green : AnsiColor() {\n            override val value: String = \"\\u001B[32m\"\n        }"
      }
    }
  ],
  "attributes": {
    "module": "kotlin-stdlib-javiersc.kotlin-stdlib.commonMain",
    "inspectionName": "UnusedSymbol"
  },
  "hash": "-6350698068453261048"
},{
  "tool": "Code Inspection",
  "category": "Redundant constructs",
  "type": "Unused symbol",
  "tags": [
    "kotlin"
  ],
  "severity": "High",
  "comment": "Object \"Yellow\" is never used",
  "detailsInfo": "Reports symbols that are not used or not reachable from entry points.",
  "sources": [
    {
      "type": "file",
      "path": "kotlin-stdlib/commonMain/kotlin/com/javiersc/kotlin/stdlib/AnsiColors.kt",
      "language": "kotlin",
      "line": 25,
      "offset": 22,
      "length": 6,
      "code": {
        "startLine": 23,
        "length": 6,
        "offset": 86,
        "surroundingCode": "            override val value: String = \"\\u001B[32m\"\n        }\n        public object Yellow : AnsiColor() {\n            override val value: String = \"\\u001B[33m\"\n        }"
      }
    }
  ],
  "attributes": {
    "module": "kotlin-stdlib-javiersc.kotlin-stdlib.commonMain",
    "inspectionName": "UnusedSymbol"
  },
  "hash": "-803494753523796517"
},{
  "tool": "Code Inspection",
  "category": "Redundant constructs",
  "type": "Unused symbol",
  "tags": [
    "kotlin"
  ],
  "severity": "High",
  "comment": "Object \"Blue\" is never used",
  "detailsInfo": "Reports symbols that are not used or not reachable from entry points.",
  "sources": [
    {
      "type": "file",
      "path": "kotlin-stdlib/commonMain/kotlin/com/javiersc/kotlin/stdlib/AnsiColors.kt",
      "language": "kotlin",
      "line": 28,
      "offset": 22,
      "length": 4,
      "code": {
        "startLine": 26,
        "length": 4,
        "offset": 86,
        "surroundingCode": "            override val value: String = \"\\u001B[33m\"\n        }\n        public object Blue : AnsiColor() {\n            override val value: String = \"\\u001B[34m\"\n        }"
      }
    }
  ],
  "attributes": {
    "module": "kotlin-stdlib-javiersc.kotlin-stdlib.commonMain",
    "inspectionName": "UnusedSymbol"
  },
  "hash": "-3394664735650932978"
},{
  "tool": "Code Inspection",
  "category": "Redundant constructs",
  "type": "Unused symbol",
  "tags": [
    "kotlin"
  ],
  "severity": "High",
  "comment": "Object \"Purple\" is never used",
  "detailsInfo": "Reports symbols that are not used or not reachable from entry points.",
  "sources": [
    {
      "type": "file",
      "path": "kotlin-stdlib/commonMain/kotlin/com/javiersc/kotlin/stdlib/AnsiColors.kt",
      "language": "kotlin",
      "line": 31,
      "offset": 22,
      "length": 6,
      "code": {
        "startLine": 29,
        "length": 6,
        "offset": 86,
        "surroundingCode": "            override val value: String = \"\\u001B[34m\"\n        }\n        public object Purple : AnsiColor() {\n            override val value: String = \"\\u001B[35m\"\n        }"
      }
    }
  ],
  "attributes": {
    "module": "kotlin-stdlib-javiersc.kotlin-stdlib.commonMain",
    "inspectionName": "UnusedSymbol"
  },
  "hash": "-6562624904909709676"
},{
  "tool": "Code Inspection",
  "category": "Redundant constructs",
  "type": "Unused symbol",
  "tags": [
    "kotlin"
  ],
  "severity": "High",
  "comment": "Object \"Cyan\" is never used",
  "detailsInfo": "Reports symbols that are not used or not reachable from entry points.",
  "sources": [
    {
      "type": "file",
      "path": "kotlin-stdlib/commonMain/kotlin/com/javiersc/kotlin/stdlib/AnsiColors.kt",
      "language": "kotlin",
      "line": 34,
      "offset": 22,
      "length": 4,
      "code": {
        "startLine": 32,
        "length": 4,
        "offset": 86,
        "surroundingCode": "            override val value: String = \"\\u001B[35m\"\n        }\n        public object Cyan : AnsiColor() {\n            override val value: String = \"\\u001B[36m\"\n        }"
      }
    }
  ],
  "attributes": {
    "module": "kotlin-stdlib-javiersc.kotlin-stdlib.commonMain",
    "inspectionName": "UnusedSymbol"
  },
  "hash": "6305750148545057673"
},{
  "tool": "Code Inspection",
  "category": "Redundant constructs",
  "type": "Unused symbol",
  "tags": [
    "kotlin"
  ],
  "severity": "High",
  "comment": "Object \"White\" is never used",
  "detailsInfo": "Reports symbols that are not used or not reachable from entry points.",
  "sources": [
    {
      "type": "file",
      "path": "kotlin-stdlib/commonMain/kotlin/com/javiersc/kotlin/stdlib/AnsiColors.kt",
      "language": "kotlin",
      "line": 37,
      "offset": 22,
      "length": 5,
      "code": {
        "startLine": 35,
        "length": 5,
        "offset": 86,
        "surroundingCode": "            override val value: String = \"\\u001B[36m\"\n        }\n        public object White : AnsiColor() {\n            override val value: String = \"\\u001B[37m\"\n        }"
      }
    }
  ],
  "attributes": {
    "module": "kotlin-stdlib-javiersc.kotlin-stdlib.commonMain",
    "inspectionName": "UnusedSymbol"
  },
  "hash": "2128543993938852000"
},{
  "tool": "Code Inspection",
  "category": "Redundant constructs",
  "type": "Unused symbol",
  "tags": [
    "kotlin"
  ],
  "severity": "High",
  "comment": "Object \"BrightBlack\" is never used",
  "detailsInfo": "Reports symbols that are not used or not reachable from entry points.",
  "sources": [
    {
      "type": "file",
      "path": "kotlin-stdlib/commonMain/kotlin/com/javiersc/kotlin/stdlib/AnsiColors.kt",
      "language": "kotlin",
      "line": 40,
      "offset": 22,
      "length": 11,
      "code": {
        "startLine": 38,
        "length": 11,
        "offset": 86,
        "surroundingCode": "            override val value: String = \"\\u001B[37m\"\n        }\n        public object BrightBlack : AnsiColor() {\n            override val value: String = \"\\u001B[90m\"\n        }"
      }
    }
  ],
  "attributes": {
    "module": "kotlin-stdlib-javiersc.kotlin-stdlib.commonMain",
    "inspectionName": "UnusedSymbol"
  },
  "hash": "7174177300055111932"
},{
  "tool": "Code Inspection",
  "category": "Redundant constructs",
  "type": "Unused symbol",
  "tags": [
    "kotlin"
  ],
  "severity": "High",
  "comment": "Object \"BrightRed\" is never used",
  "detailsInfo": "Reports symbols that are not used or not reachable from entry points.",
  "sources": [
    {
      "type": "file",
      "path": "kotlin-stdlib/commonMain/kotlin/com/javiersc/kotlin/stdlib/AnsiColors.kt",
      "language": "kotlin",
      "line": 43,
      "offset": 22,
      "length": 9,
      "code": {
        "startLine": 41,
        "length": 9,
        "offset": 86,
        "surroundingCode": "            override val value: String = \"\\u001B[90m\"\n        }\n        public object BrightRed : AnsiColor() {\n            override val value: String = \"\\u001B[91m\"\n        }"
      }
    }
  ],
  "attributes": {
    "module": "kotlin-stdlib-javiersc.kotlin-stdlib.commonMain",
    "inspectionName": "UnusedSymbol"
  },
  "hash": "8554113948490642890"
},{
  "tool": "Code Inspection",
  "category": "Redundant constructs",
  "type": "Unused symbol",
  "tags": [
    "kotlin"
  ],
  "severity": "High",
  "comment": "Object \"BrightGreen\" is never used",
  "detailsInfo": "Reports symbols that are not used or not reachable from entry points.",
  "sources": [
    {
      "type": "file",
      "path": "kotlin-stdlib/commonMain/kotlin/com/javiersc/kotlin/stdlib/AnsiColors.kt",
      "language": "kotlin",
      "line": 46,
      "offset": 22,
      "length": 11,
      "code": {
        "startLine": 44,
        "length": 11,
        "offset": 86,
        "surroundingCode": "            override val value: String = \"\\u001B[91m\"\n        }\n        public object BrightGreen : AnsiColor() {\n            override val value: String = \"\\u001B[92m\"\n        }"
      }
    }
  ],
  "attributes": {
    "module": "kotlin-stdlib-javiersc.kotlin-stdlib.commonMain",
    "inspectionName": "UnusedSymbol"
  },
  "hash": "-7507949251871788374"
},{
  "tool": "Code Inspection",
  "category": "Redundant constructs",
  "type": "Unused symbol",
  "tags": [
    "kotlin"
  ],
  "severity": "High",
  "comment": "Object \"BrightYellow\" is never used",
  "detailsInfo": "Reports symbols that are not used or not reachable from entry points.",
  "sources": [
    {
      "type": "file",
      "path": "kotlin-stdlib/commonMain/kotlin/com/javiersc/kotlin/stdlib/AnsiColors.kt",
      "language": "kotlin",
      "line": 49,
      "offset": 22,
      "length": 12,
      "code": {
        "startLine": 47,
        "length": 12,
        "offset": 86,
        "surroundingCode": "            override val value: String = \"\\u001B[92m\"\n        }\n        public object BrightYellow : AnsiColor() {\n            override val value: String = \"\\u001B[93m\"\n        }"
      }
    }
  ],
  "attributes": {
    "module": "kotlin-stdlib-javiersc.kotlin-stdlib.commonMain",
    "inspectionName": "UnusedSymbol"
  },
  "hash": "9134798790573991385"
},{
  "tool": "Code Inspection",
  "category": "Redundant constructs",
  "type": "Unused symbol",
  "tags": [
    "kotlin"
  ],
  "severity": "High",
  "comment": "Object \"BrightBlue\" is never used",
  "detailsInfo": "Reports symbols that are not used or not reachable from entry points.",
  "sources": [
    {
      "type": "file",
      "path": "kotlin-stdlib/commonMain/kotlin/com/javiersc/kotlin/stdlib/AnsiColors.kt",
      "language": "kotlin",
      "line": 52,
      "offset": 22,
      "length": 10,
      "code": {
        "startLine": 50,
        "length": 10,
        "offset": 86,
        "surroundingCode": "            override val value: String = \"\\u001B[93m\"\n        }\n        public object BrightBlue : AnsiColor() {\n            override val value: String = \"\\u001B[94m\"\n        }"
      }
    }
  ],
  "attributes": {
    "module": "kotlin-stdlib-javiersc.kotlin-stdlib.commonMain",
    "inspectionName": "UnusedSymbol"
  },
  "hash": "-6208283183643932369"
},{
  "tool": "Code Inspection",
  "category": "Redundant constructs",
  "type": "Unused symbol",
  "tags": [
    "kotlin"
  ],
  "severity": "High",
  "comment": "Object \"BrightPurple\" is never used",
  "detailsInfo": "Reports symbols that are not used or not reachable from entry points.",
  "sources": [
    {
      "type": "file",
      "path": "kotlin-stdlib/commonMain/kotlin/com/javiersc/kotlin/stdlib/AnsiColors.kt",
      "language": "kotlin",
      "line": 55,
      "offset": 22,
      "length": 12,
      "code": {
        "startLine": 53,
        "length": 12,
        "offset": 86,
        "surroundingCode": "            override val value: String = \"\\u001B[94m\"\n        }\n        public object BrightPurple : AnsiColor() {\n            override val value: String = \"\\u001B[95m\"\n        }"
      }
    }
  ],
  "attributes": {
    "module": "kotlin-stdlib-javiersc.kotlin-stdlib.commonMain",
    "inspectionName": "UnusedSymbol"
  },
  "hash": "4835370437154982973"
},{
  "tool": "Code Inspection",
  "category": "Redundant constructs",
  "type": "Unused symbol",
  "tags": [
    "kotlin"
  ],
  "severity": "High",
  "comment": "Object \"BrightCyan\" is never used",
  "detailsInfo": "Reports symbols that are not used or not reachable from entry points.",
  "sources": [
    {
      "type": "file",
      "path": "kotlin-stdlib/commonMain/kotlin/com/javiersc/kotlin/stdlib/AnsiColors.kt",
      "language": "kotlin",
      "line": 58,
      "offset": 22,
      "length": 10,
      "code": {
        "startLine": 56,
        "length": 10,
        "offset": 86,
        "surroundingCode": "            override val value: String = \"\\u001B[95m\"\n        }\n        public object BrightCyan : AnsiColor() {\n            override val value: String = \"\\u001B[96m\"\n        }"
      }
    }
  ],
  "attributes": {
    "module": "kotlin-stdlib-javiersc.kotlin-stdlib.commonMain",
    "inspectionName": "UnusedSymbol"
  },
  "hash": "7245327324769306338"
},{
  "tool": "Code Inspection",
  "category": "Redundant constructs",
  "type": "Unused symbol",
  "tags": [
    "kotlin"
  ],
  "severity": "High",
  "comment": "Object \"BrightWhite\" is never used",
  "detailsInfo": "Reports symbols that are not used or not reachable from entry points.",
  "sources": [
    {
      "type": "file",
      "path": "kotlin-stdlib/commonMain/kotlin/com/javiersc/kotlin/stdlib/AnsiColors.kt",
      "language": "kotlin",
      "line": 61,
      "offset": 22,
      "length": 11,
      "code": {
        "startLine": 59,
        "length": 11,
        "offset": 86,
        "surroundingCode": "            override val value: String = \"\\u001B[96m\"\n        }\n        public object BrightWhite : AnsiColor() {\n            override val value: String = \"\\u001B[97m\"\n        }"
      }
    }
  ],
  "attributes": {
    "module": "kotlin-stdlib-javiersc.kotlin-stdlib.commonMain",
    "inspectionName": "UnusedSymbol"
  },
  "hash": "-5547235954675119439"
},{
  "tool": "Code Inspection",
  "category": "Redundant constructs",
  "type": "Unused symbol",
  "tags": [
    "kotlin"
  ],
  "severity": "High",
  "comment": "Object \"Background\" is never used",
  "detailsInfo": "Reports symbols that are not used or not reachable from entry points.",
  "sources": [
    {
      "type": "file",
      "path": "kotlin-stdlib/commonMain/kotlin/com/javiersc/kotlin/stdlib/AnsiColors.kt",
      "language": "kotlin",
      "line": 66,
      "offset": 18,
      "length": 10,
      "code": {
        "startLine": 64,
        "length": 10,
        "offset": 25,
        "surroundingCode": "    }\n\n    public object Background {\n        public object Black : AnsiColor() {\n            override val value: String = \"\\u001B[40m\""
      }
    }
  ],
  "attributes": {
    "module": "kotlin-stdlib-javiersc.kotlin-stdlib.commonMain",
    "inspectionName": "UnusedSymbol"
  },
  "hash": "-8891349638824238000"
},{
  "tool": "Code Inspection",
  "category": "Redundant constructs",
  "type": "Unused symbol",
  "tags": [
    "kotlin"
  ],
  "severity": "High",
  "comment": "Object \"Black\" is never used",
  "detailsInfo": "Reports symbols that are not used or not reachable from entry points.",
  "sources": [
    {
      "type": "file",
      "path": "kotlin-stdlib/commonMain/kotlin/com/javiersc/kotlin/stdlib/AnsiColors.kt",
      "language": "kotlin",
      "line": 67,
      "offset": 22,
      "length": 5,
      "code": {
        "startLine": 65,
        "length": 5,
        "offset": 54,
        "surroundingCode": "\n    public object Background {\n        public object Black : AnsiColor() {\n            override val value: String = \"\\u001B[40m\"\n        }"
      }
    }
  ],
  "attributes": {
    "module": "kotlin-stdlib-javiersc.kotlin-stdlib.commonMain",
    "inspectionName": "UnusedSymbol"
  },
  "hash": "6491244033195626579"
},{
  "tool": "Code Inspection",
  "category": "Redundant constructs",
  "type": "Unused symbol",
  "tags": [
    "kotlin"
  ],
  "severity": "High",
  "comment": "Object \"Red\" is never used",
  "detailsInfo": "Reports symbols that are not used or not reachable from entry points.",
  "sources": [
    {
      "type": "file",
      "path": "kotlin-stdlib/commonMain/kotlin/com/javiersc/kotlin/stdlib/AnsiColors.kt",
      "language": "kotlin",
      "line": 70,
      "offset": 22,
      "length": 3,
      "code": {
        "startLine": 68,
        "length": 3,
        "offset": 86,
        "surroundingCode": "            override val value: String = \"\\u001B[40m\"\n        }\n        public object Red : AnsiColor() {\n            override val value: String = \"\\u001B[41m\"\n        }"
      }
    }
  ],
  "attributes": {
    "module": "kotlin-stdlib-javiersc.kotlin-stdlib.commonMain",
    "inspectionName": "UnusedSymbol"
  },
  "hash": "8554465656506914109"
},{
  "tool": "Code Inspection",
  "category": "Redundant constructs",
  "type": "Unused symbol",
  "tags": [
    "kotlin"
  ],
  "severity": "High",
  "comment": "Object \"Green\" is never used",
  "detailsInfo": "Reports symbols that are not used or not reachable from entry points.",
  "sources": [
    {
      "type": "file",
      "path": "kotlin-stdlib/commonMain/kotlin/com/javiersc/kotlin/stdlib/AnsiColors.kt",
      "language": "kotlin",
      "line": 73,
      "offset": 22,
      "length": 5,
      "code": {
        "startLine": 71,
        "length": 5,
        "offset": 86,
        "surroundingCode": "            override val value: String = \"\\u001B[41m\"\n        }\n        public object Green : AnsiColor() {\n            override val value: String = \"\\u001B[42m\"\n        }"
      }
    }
  ],
  "attributes": {
    "module": "kotlin-stdlib-javiersc.kotlin-stdlib.commonMain",
    "inspectionName": "UnusedSymbol"
  },
  "hash": "3905292913305101123"
},{
  "tool": "Code Inspection",
  "category": "Redundant constructs",
  "type": "Unused symbol",
  "tags": [
    "kotlin"
  ],
  "severity": "High",
  "comment": "Object \"Yellow\" is never used",
  "detailsInfo": "Reports symbols that are not used or not reachable from entry points.",
  "sources": [
    {
      "type": "file",
      "path": "kotlin-stdlib/commonMain/kotlin/com/javiersc/kotlin/stdlib/AnsiColors.kt",
      "language": "kotlin",
      "line": 76,
      "offset": 22,
      "length": 6,
      "code": {
        "startLine": 74,
        "length": 6,
        "offset": 86,
        "surroundingCode": "            override val value: String = \"\\u001B[42m\"\n        }\n        public object Yellow : AnsiColor() {\n            override val value: String = \"\\u001b[43m\"\n        }"
      }
    }
  ],
  "attributes": {
    "module": "kotlin-stdlib-javiersc.kotlin-stdlib.commonMain",
    "inspectionName": "UnusedSymbol"
  },
  "hash": "2844543985770581575"
},{
  "tool": "Code Inspection",
  "category": "Redundant constructs",
  "type": "Unused symbol",
  "tags": [
    "kotlin"
  ],
  "severity": "High",
  "comment": "Object \"Blue\" is never used",
  "detailsInfo": "Reports symbols that are not used or not reachable from entry points.",
  "sources": [
    {
      "type": "file",
      "path": "kotlin-stdlib/commonMain/kotlin/com/javiersc/kotlin/stdlib/AnsiColors.kt",
      "language": "kotlin",
      "line": 79,
      "offset": 22,
      "length": 4,
      "code": {
        "startLine": 77,
        "length": 4,
        "offset": 86,
        "surroundingCode": "            override val value: String = \"\\u001b[43m\"\n        }\n        public object Blue : AnsiColor() {\n            override val value: String = \"\\u001B[44m\"\n        }"
      }
    }
  ],
  "attributes": {
    "module": "kotlin-stdlib-javiersc.kotlin-stdlib.commonMain",
    "inspectionName": "UnusedSymbol"
  },
  "hash": "-8058942605699967633"
},{
  "tool": "Code Inspection",
  "category": "Redundant constructs",
  "type": "Unused symbol",
  "tags": [
    "kotlin"
  ],
  "severity": "High",
  "comment": "Object \"Purple\" is never used",
  "detailsInfo": "Reports symbols that are not used or not reachable from entry points.",
  "sources": [
    {
      "type": "file",
      "path": "kotlin-stdlib/commonMain/kotlin/com/javiersc/kotlin/stdlib/AnsiColors.kt",
      "language": "kotlin",
      "line": 82,
      "offset": 22,
      "length": 6,
      "code": {
        "startLine": 80,
        "length": 6,
        "offset": 86,
        "surroundingCode": "            override val value: String = \"\\u001B[44m\"\n        }\n        public object Purple : AnsiColor() {\n            override val value: String = \"\\u001B[45m\"\n        }"
      }
    }
  ],
  "attributes": {
    "module": "kotlin-stdlib-javiersc.kotlin-stdlib.commonMain",
    "inspectionName": "UnusedSymbol"
  },
  "hash": "-1404036477270516594"
},{
  "tool": "Code Inspection",
  "category": "Redundant constructs",
  "type": "Unused symbol",
  "tags": [
    "kotlin"
  ],
  "severity": "High",
  "comment": "Object \"Cyan\" is never used",
  "detailsInfo": "Reports symbols that are not used or not reachable from entry points.",
  "sources": [
    {
      "type": "file",
      "path": "kotlin-stdlib/commonMain/kotlin/com/javiersc/kotlin/stdlib/AnsiColors.kt",
      "language": "kotlin",
      "line": 85,
      "offset": 22,
      "length": 4,
      "code": {
        "startLine": 83,
        "length": 4,
        "offset": 86,
        "surroundingCode": "            override val value: String = \"\\u001B[45m\"\n        }\n        public object Cyan : AnsiColor() {\n            override val value: String = \"\\u001B[46m\"\n        }"
      }
    }
  ],
  "attributes": {
    "module": "kotlin-stdlib-javiersc.kotlin-stdlib.commonMain",
    "inspectionName": "UnusedSymbol"
  },
  "hash": "6243776718284447200"
},{
  "tool": "Code Inspection",
  "category": "Redundant constructs",
  "type": "Unused symbol",
  "tags": [
    "kotlin"
  ],
  "severity": "High",
  "comment": "Object \"Gray\" is never used",
  "detailsInfo": "Reports symbols that are not used or not reachable from entry points.",
  "sources": [
    {
      "type": "file",
      "path": "kotlin-stdlib/commonMain/kotlin/com/javiersc/kotlin/stdlib/AnsiColors.kt",
      "language": "kotlin",
      "line": 88,
      "offset": 22,
      "length": 4,
      "code": {
        "startLine": 86,
        "length": 4,
        "offset": 86,
        "surroundingCode": "            override val value: String = \"\\u001B[46m\"\n        }\n        public object Gray : AnsiColor() {\n            override val value: String = \"\\u001B[47m\"\n        }"
      }
    }
  ],
  "attributes": {
    "module": "kotlin-stdlib-javiersc.kotlin-stdlib.commonMain",
    "inspectionName": "UnusedSymbol"
  },
  "hash": "-5220776677014263221"
}]}